tenforce/__init__.py
tenforce/enforcer.c
tenforce/enforcer.cpython-311-darwin.so
tenforce/enforcer.pyx
tenforce/exceptions.py
tenforce-0.1.2.dist-info/LICENSE.md
tenforce-0.1.2.dist-info/METADATA
tenforce-0.1.2.dist-info/WHEEL
tenforce-0.1.2.dist-info/top_level.txt
tenforce-0.1.2.dist-info/RECORD
