Metadata-Version: 2.1
Name: tenforce
Version: 0.1.2
Summary: Type enforcement for Python
License: MIT License
Requires-Python: >=3.11
License-File: LICENSE.md
